LICENSE
LICENSE_dependencies
README.md
setup.py
bin/ilund4u
ilund4u/__init__.py
ilund4u/data_manager.py
ilund4u/data_processing.py
ilund4u/drawing.py
ilund4u/manager.py
ilund4u/methods.py
ilund4u.egg-info/PKG-INFO
ilund4u.egg-info/SOURCES.txt
ilund4u.egg-info/dependency_links.txt
ilund4u.egg-info/not-zip-safe
ilund4u.egg-info/requires.txt
ilund4u.egg-info/top_level.txt
ilund4u/../docs/pypi.md
ilund4u/ilund4u_data/.DS_Store
ilund4u/ilund4u_data/category_colours_proteome_groups.tsv
ilund4u/ilund4u_data/help_hotspots.txt
ilund4u/ilund4u_data/help_main.txt
ilund4u/ilund4u_data/help_protein.txt
ilund4u/ilund4u_data/help_proteome.txt
ilund4u/ilund4u_data/standard.cfg
ilund4u/ilund4u_data/bin/.DS_Store
ilund4u/ilund4u_data/bin/mmseqs_linux.zip
ilund4u/ilund4u_data/bin/mmseqs_mac/.DS_Store
ilund4u/ilund4u_data/bin/mmseqs_mac/LICENSE.md
ilund4u/ilund4u_data/bin/mmseqs_mac/README.md
ilund4u/ilund4u_data/bin/mmseqs_mac/userguide.pdf
ilund4u/ilund4u_data/bin/mmseqs_mac/bin/mmseqs
ilund4u/ilund4u_data/bin/mmseqs_mac/examples/DB.fasta
ilund4u/ilund4u_data/bin/mmseqs_mac/examples/QUERY.fasta
ilund4u/ilund4u_data/bin/mmseqs_mac/matrices/PAM10.out
ilund4u/ilund4u_data/bin/mmseqs_mac/matrices/PAM100.out
ilund4u/ilund4u_data/bin/mmseqs_mac/matrices/PAM110.out
ilund4u/ilund4u_data/bin/mmseqs_mac/matrices/PAM120.out
ilund4u/ilund4u_data/bin/mmseqs_mac/matrices/PAM130.out
ilund4u/ilund4u_data/bin/mmseqs_mac/matrices/PAM140.out
ilund4u/ilund4u_data/bin/mmseqs_mac/matrices/PAM150.out
ilund4u/ilund4u_data/bin/mmseqs_mac/matrices/PAM160.out
ilund4u/ilund4u_data/bin/mmseqs_mac/matrices/PAM170.out
ilund4u/ilund4u_data/bin/mmseqs_mac/matrices/PAM180.out
ilund4u/ilund4u_data/bin/mmseqs_mac/matrices/PAM190.out
ilund4u/ilund4u_data/bin/mmseqs_mac/matrices/PAM20.out
ilund4u/ilund4u_data/bin/mmseqs_mac/matrices/PAM30.out
ilund4u/ilund4u_data/bin/mmseqs_mac/matrices/PAM40.out
ilund4u/ilund4u_data/bin/mmseqs_mac/matrices/PAM50.out
ilund4u/ilund4u_data/bin/mmseqs_mac/matrices/PAM60.out
ilund4u/ilund4u_data/bin/mmseqs_mac/matrices/PAM70.out
ilund4u/ilund4u_data/bin/mmseqs_mac/matrices/PAM80.out
ilund4u/ilund4u_data/bin/mmseqs_mac/matrices/PAM90.out
