Metadata-Version: 2.4
Name: ilund4u
Version: 0.1.4.2.1
Summary: description
Home-page: https://art-egorov.github.io/ilund4u/
Author: Artyom Egorov
Author-email: artem.egorov@med.lu.se
License: WTFPL
Requires-Python: >=3.8
License-File: LICENSE
License-File: LICENSE_dependencies
Requires-Dist: biopython
Requires-Dist: requests
Requires-Dist: configs
Requires-Dist: pandas
Requires-Dist: bcbio-gff
Requires-Dist: matplotlib
Requires-Dist: seaborn
Requires-Dist: scipy
Requires-Dist: msa4u
Requires-Dist: lovis4u
Requires-Dist: progress
Requires-Dist: leidenalg
Requires-Dist: igraph
Requires-Dist: pyhmmer>=0.12.0
Dynamic: author
Dynamic: author-email
Dynamic: description
Dynamic: description-content-type
Dynamic: home-page
Dynamic: license
Dynamic: license-file
Dynamic: requires-dist
Dynamic: requires-python
Dynamic: summary
